gene2word/__init__.py
gene2word/_source.py
gene2word/_sqlite.py
gene2word/data.7z
gene2word/exceptions.py
gene2word/getArticle.py
gene2word/jarvispatrick.py
gene2word/queryWord.py
gene2word-2.0.0a1.dist-info/LICENSE
gene2word-2.0.0a1.dist-info/METADATA
gene2word-2.0.0a1.dist-info/WHEEL
gene2word-2.0.0a1.dist-info/top_level.txt
gene2word-2.0.0a1.dist-info/RECORD
